media_catalog/__init__.py
media_catalog/__main__.py
media_catalog/cli.py
media_catalog/epub.py
media_catalog/merge.py
media_catalog/omdb.py
media_catalog/poster.py
media_catalog/render.py
media_catalog/util.py
media_catalog/data/afi_top_100_1998.csv
media_catalog/data/afi_top_100_2007.csv
media_catalog/data/bfi_sight_sound.csv
media_catalog/data/cannes_palme_dor.csv
media_catalog/data/imdb_top_250.csv
media_catalog/data/imdb_top_250_tv.csv
mediacatalog-0.1.1.dist-info/licenses/LICENSE
samples/catalog.epub
samples/catalog.pdf
mediacatalog-0.1.1.dist-info/METADATA
mediacatalog-0.1.1.dist-info/WHEEL
mediacatalog-0.1.1.dist-info/entry_points.txt
mediacatalog-0.1.1.dist-info/top_level.txt
mediacatalog-0.1.1.dist-info/RECORD
