Metadata-Version: 2.4
Name: mediacatalog
Version: 0.1.1
Summary: Generate printable A5 pages and EPUBs for a media catalog from a CSV of IMDb IDs.
Author: Mathew Brown
License:                     GNU GENERAL PUBLIC LICENSE
Classifier: Development Status :: 3 - Alpha
Classifier: Environment :: Console
Classifier: Intended Audience :: End Users/Desktop
Classifier: License :: OSI Approved :: GNU General Public License v3 or later (GPLv3+)
Classifier: Programming Language :: Python :: 3
Classifier: Programming Language :: Python :: 3 :: Only
Classifier: Programming Language :: Python :: 3.10
Classifier: Programming Language :: Python :: 3.11
Classifier: Programming Language :: Python :: 3.12
Classifier: Programming Language :: Python :: 3.13
Requires-Python: >=3.10
License-File: LICENSE
Requires-Dist: pypdf>=4.0.0
Requires-Dist: reportlab>=4.0.0
Requires-Dist: requests>=2.31.0
Requires-Dist: python-dotenv>=1.0.1
Requires-Dist: ebooklib>=0.18
Dynamic: license-file
